djprod/__init__.py
djprod/cli.py
djprod/core.py
djprod/env_checker.py
djprod/utils.py
djprod-0.2.2.dist-info/licenses/LICENSE
templates/env.example
templates/manage.py
templates/core/__init__.py
templates/core/asgi.py
templates/core/env.py
templates/core/urls.py
templates/core/wsgi.py
templates/core/django/__init__.py
templates/core/django/base.py
templates/core/django/local.py
templates/core/django/production.py
templates/core/django/tests.py
templates/core/middleware/__init__.py
templates/core/settings/__init__.py
templates/core/settings/celery.py
templates/core/settings/cors.py
templates/core/settings/s3_storage.py
templates/core/settings/sentry.py
templates/core/settings/sessions.py
templates/static/css/base.css
templates/static/js/base.js
templates/templates/base.html
templates/templates/djprod.html
djprod-0.2.2.dist-info/METADATA
djprod-0.2.2.dist-info/WHEEL
djprod-0.2.2.dist-info/entry_points.txt
djprod-0.2.2.dist-info/top_level.txt
djprod-0.2.2.dist-info/RECORD
