Metadata-Version: 2.4
Name: djprod
Version: 0.2.2
Summary: Yet another production-ready Django project.
Author-email: Ali Hassan <alihassan.pyc@gmail.com>
License-Expression: MIT
Project-URL: Homepage, https://github.com/elly-hacen/djprod
Project-URL: Repository, https://github.com/elly-hacen/djprod
Project-URL: Issues, https://github.com/elly-hacen/djprod/issues
Requires-Python: >=3.11
License-File: LICENSE
Requires-Dist: django
Requires-Dist: django-environ
Requires-Dist: psycopg2-binary
Requires-Dist: rich
Dynamic: license-file
